{
  "v": "5.9.6",
  "fr": 30,
  "ip": 0,
  "op": 120,
  "w": 300,
  "h": 300,
  "nm": "Neon Glow Ring",
  "layers": [
    {
      "ty": 4,
      "nm": "Ring 1",
      "sr": 1,
      "ks": {
        "o": { "a": 1, "k": [{ "t": 0, "s": [30], "e": [80] }, { "t": 60, "s": [80], "e": [30] }, { "t": 120, "s": [30] }] },
        "r": { "a": 1, "k": [{ "t": 0, "s": [0], "e": [360] }, { "t": 120, "s": [360] }] },
        "p": { "a": 0, "k": [150, 150] },
        "a": { "a": 0, "k": [0, 0] },
        "s": { "a": 1, "k": [{ "t": 0, "s": [95, 95], "e": [105, 105] }, { "t": 60, "s": [105, 105], "e": [95, 95] }, { "t": 120, "s": [95, 95] }] }
      },
      "shapes": [
        { "ty": "el", "p": { "a": 0, "k": [0, 0] }, "s": { "a": 0, "k": [260, 260] } },
        {
          "ty": "st",
          "c": { "a": 0, "k": [0, 0.94, 1, 1] },
          "o": { "a": 0, "k": 100 },
          "w": { "a": 0, "k": 3 },
          "d": [
            { "n": "d", "nm": "dash", "v": { "a": 0, "k": 20 } },
            { "n": "g", "nm": "gap", "v": { "a": 0, "k": 15 } },
            { "n": "o", "nm": "offset", "v": { "a": 1, "k": [{ "t": 0, "s": [0], "e": [100] }, { "t": 120, "s": [100] }] } }
          ]
        }
      ],
      "ip": 0, "op": 120
    },
    {
      "ty": 4,
      "nm": "Ring 2",
      "sr": 1,
      "ks": {
        "o": { "a": 1, "k": [{ "t": 0, "s": [50], "e": [90] }, { "t": 60, "s": [90], "e": [50] }, { "t": 120, "s": [50] }] },
        "r": { "a": 1, "k": [{ "t": 0, "s": [0], "e": [-360] }, { "t": 120, "s": [-360] }] },
        "p": { "a": 0, "k": [150, 150] },
        "a": { "a": 0, "k": [0, 0] },
        "s": { "a": 0, "k": [100, 100] }
      },
      "shapes": [
        { "ty": "el", "p": { "a": 0, "k": [0, 0] }, "s": { "a": 0, "k": [220, 220] } },
        {
          "ty": "st",
          "c": { "a": 0, "k": [0, 0.4, 1, 1] },
          "o": { "a": 0, "k": 100 },
          "w": { "a": 0, "k": 2.5 },
          "d": [
            { "n": "d", "nm": "dash", "v": { "a": 0, "k": 30 } },
            { "n": "g", "nm": "gap", "v": { "a": 0, "k": 25 } },
            { "n": "o", "nm": "offset", "v": { "a": 1, "k": [{ "t": 0, "s": [0], "e": [-80] }, { "t": 120, "s": [-80] }] } }
          ]
        }
      ],
      "ip": 0, "op": 120
    },
    {
      "ty": 4,
      "nm": "Ring 3",
      "sr": 1,
      "ks": {
        "o": { "a": 1, "k": [{ "t": 0, "s": [40], "e": [70] }, { "t": 60, "s": [70], "e": [40] }, { "t": 120, "s": [40] }] },
        "r": { "a": 1, "k": [{ "t": 0, "s": [0], "e": [180] }, { "t": 120, "s": [180] }] },
        "p": { "a": 0, "k": [150, 150] },
        "a": { "a": 0, "k": [0, 0] },
        "s": { "a": 0, "k": [100, 100] }
      },
      "shapes": [
        { "ty": "el", "p": { "a": 0, "k": [0, 0] }, "s": { "a": 0, "k": [180, 180] } },
        {
          "ty": "st",
          "c": { "a": 0, "k": [0.55, 0, 1, 1] },
          "o": { "a": 0, "k": 100 },
          "w": { "a": 0, "k": 2 },
          "d": [
            { "n": "d", "nm": "dash", "v": { "a": 0, "k": 15 } },
            { "n": "g", "nm": "gap", "v": { "a": 0, "k": 20 } },
            { "n": "o", "nm": "offset", "v": { "a": 1, "k": [{ "t": 0, "s": [0], "e": [60] }, { "t": 120, "s": [60] }] } }
          ]
        }
      ],
      "ip": 0, "op": 120
    },
    {
      "ty": 4,
      "nm": "Inner Glow",
      "sr": 1,
      "ks": {
        "o": { "a": 1, "k": [{ "t": 0, "s": [20], "e": [60] }, { "t": 30, "s": [60], "e": [20] }, { "t": 60, "s": [20], "e": [60] }, { "t": 90, "s": [60], "e": [20] }, { "t": 120, "s": [20] }] },
        "r": { "a": 0, "k": 0 },
        "p": { "a": 0, "k": [150, 150] },
        "a": { "a": 0, "k": [0, 0] },
        "s": { "a": 1, "k": [{ "t": 0, "s": [80, 80], "e": [110, 110] }, { "t": 60, "s": [110, 110], "e": [80, 80] }, { "t": 120, "s": [80, 80] }] }
      },
      "shapes": [
        { "ty": "el", "p": { "a": 0, "k": [0, 0] }, "s": { "a": 0, "k": [100, 100] } },
        { "ty": "fl", "c": { "a": 0, "k": [0, 0.94, 1, 0.15] }, "o": { "a": 0, "k": 100 } }
      ],
      "ip": 0, "op": 120
    }
  ]
}
